{"v":"5.1.10","fr":60,"ip":0,"op":241,"w":300,"h":300,"nm":"White Flower","ddd":0,"assets":[{"id":"comp_0","layers":[{"ddd":0,"ind":1,"ty":0,"nm":"white flower half","parent":3,"refId":"comp_1","sr":1,"ks":{"o":{"a":0,"k":100,"ix":11},"r":{"a":0,"k":0,"ix":10},"p":{"a":0,"k":[3.79,2.791,0],"ix":2},"a":{"a":0,"k":[55.525,54.575,0],"ix":1},"s":{"a":0,"k":[100,100,100],"ix":6}},"ao":0,"w":116,"h":117,"ip":61,"op":265,"st":61,"bm":0},{"ddd":0,"ind":2,"ty":4,"nm":"flower bud 2","parent":3,"sr":1,"ks":{"o":{"a":0,"k":100,"ix":11},"r":{"a":1,"k":[{"i":{"x":[0.667],"y":[1]},"o":{"x":[0.333],"y":[0]},"n":["0p667_1_0p333_0"],"t":61,"s":[-33],"e":[-10]},{"t":62}],"ix":10},"p":{"a":1,"k":[{"i":{"x":0.667,"y":1},"o":{"x":0.333,"y":0},"n":"0p667_1_0p333_0","t":0,"s":[82.352,114.854,0],"e":[5.473,5.443,0],"to":[0,0,0],"ti":[38.4400024414063,78.2499847412109,0]},{"t":61}],"ix":2},"a":{"a":0,"k":[19.784,-61.88,0],"ix":1},"s":{"a":1,"k":[{"i":{"x":[0.667,0.667,0.667],"y":[1,1,1]},"o":{"x":[0.333,0.333,0.333],"y":[0,0,0]},"n":["0p667_1_0p333_0","0p667_1_0p333_0","0p667_1_0p333_0"],"t":15,"s":[0,0,100],"e":[30,30,100]},{"t":61}],"ix":6}},"ao":0,"shapes":[{"ty":"gr","it":[{"ind":0,"ty":"sh","ix":1,"ks":{"a":0,"k":{"i":[[2.75,1.75],[-4.25,-3.25]],"o":[[-2.75,-1.75],[4.25,3.25]],"v":[[25.75,-74.5],[19.5,-62.25]],"c":true},"ix":2},"nm":"Path 1","mn":"ADBE Vector Shape - Group","hd":false},{"ty":"fl","c":{"a":0,"k":[1,1,1,1],"ix":4},"o":{"a":0,"k":100,"ix":5},"r":1,"nm":"Fill 1","mn":"ADBE Vector Graphic - Fill","hd":false},{"ty":"tr","p":{"a":0,"k":[0,0],"ix":2},"a":{"a":0,"k":[0,0],"ix":1},"s":{"a":0,"k":[100,100],"ix":3},"r":{"a":0,"k":0,"ix":6},"o":{"a":0,"k":100,"ix":7},"sk":{"a":0,"k":0,"ix":4},"sa":{"a":0,"k":0,"ix":5},"nm":"Transform"}],"nm":"Shape 1","np":3,"cix":2,"ix":1,"mn":"ADBE Vector Group","hd":false}],"ip":0,"op":337,"st":0,"bm":0},{"ddd":0,"ind":3,"ty":4,"nm":"scape2","sr":1,"ks":{"o":{"a":0,"k":100,"ix":11},"r":{"a":1,"k":[{"i":{"x":[0.667],"y":[1]},"o":{"x":[0.333],"y":[0]},"n":["0p667_1_0p333_0"],"t":0,"s":[0],"e":[5]},{"i":{"x":[0.667],"y":[1]},"o":{"x":[0.333],"y":[0]},"n":["0p667_1_0p333_0"],"t":70,"s":[5],"e":[-2]},{"i":{"x":[0.667],"y":[1]},"o":{"x":[0.333],"y":[0]},"n":["0p667_1_0p333_0"],"t":131,"s":[-2],"e":[3]},{"i":{"x":[0.667],"y":[1]},"o":{"x":[0.333],"y":[0]},"n":["0p667_1_0p333_0"],"t":192,"s":[3],"e":[-2]},{"t":252}],"ix":10},"p":{"a":0,"k":[158.717,247.762,0],"ix":2},"a":{"a":0,"k":[82.189,114.706,0],"ix":1},"s":{"a":0,"k":[100,100,100],"ix":6}},"ao":0,"shapes":[{"ty":"gr","it":[{"ind":0,"ty":"sh","ix":1,"ks":{"a":0,"k":{"i":[[0,0],[38.44,78.25]],"o":[[0,0],[0,0]],"v":[[38.439,54.706],[-38.439,-54.706]],"c":false},"ix":2},"nm":"Path 1","mn":"ADBE Vector Shape - Group","hd":false},{"ty":"st","c":{"a":0,"k":[0.311000001197,0.119999994016,0.215000002992,1],"ix":3},"o":{"a":0,"k":100,"ix":4},"w":{"a":0,"k":1.2,"ix":5},"lc":2,"lj":1,"ml":10,"nm":"Stroke 1","mn":"ADBE Vector Graphic - Stroke","hd":false},{"ty":"tr","p":{"a":0,"k":[43.439,59.706],"ix":2},"a":{"a":0,"k":[0,0],"ix":1},"s":{"a":0,"k":[100,100],"ix":3},"r":{"a":0,"k":0,"ix":6},"o":{"a":0,"k":100,"ix":7},"sk":{"a":0,"k":0,"ix":4},"sa":{"a":0,"k":0,"ix":5},"nm":"Transform"}],"nm":"Group 1","np":2,"cix":2,"ix":1,"mn":"ADBE Vector Group","hd":false},{"ty":"tm","s":{"a":0,"k":0,"ix":1},"e":{"a":1,"k":[{"i":{"x":[0.667],"y":[1]},"o":{"x":[0.333],"y":[0]},"n":["0p667_1_0p333_0"],"t":0,"s":[0],"e":[100]},{"t":61}],"ix":2},"o":{"a":0,"k":0,"ix":3},"m":1,"ix":2,"nm":"Trim Paths 1","mn":"ADBE Vector Filter - Trim","hd":false}],"ip":0,"op":337,"st":0,"bm":0}]},{"id":"comp_1","layers":[{"ddd":0,"ind":1,"ty":4,"nm":"pistil","sr":1,"ks":{"o":{"a":0,"k":100,"ix":11},"r":{"a":1,"k":[{"i":{"x":[0.667],"y":[1]},"o":{"x":[0.333],"y":[0]},"n":["0p667_1_0p333_0"],"t":0,"s":[0],"e":[5]},{"i":{"x":[0.667],"y":[1]},"o":{"x":[0.333],"y":[0]},"n":["0p667_1_0p333_0"],"t":45,"s":[5],"e":[-5]},{"i":{"x":[0.667],"y":[1]},"o":{"x":[0.333],"y":[0]},"n":["0p667_1_0p333_0"],"t":93,"s":[-5],"e":[5]},{"i":{"x":[0.667],"y":[1]},"o":{"x":[0.333],"y":[0]},"n":["0p667_1_0p333_0"],"t":149,"s":[5],"e":[-5]},{"t":197}],"ix":10},"p":{"a":0,"k":[55.996,54.447,0],"ix":2},"a":{"a":0,"k":[10.99,8.851,0],"ix":1},"s":{"a":1,"k":[{"i":{"x":[0.667,0.667,0.667],"y":[1,1,1]},"o":{"x":[0.333,0.333,0.333],"y":[0,0,0]},"n":["0p667_1_0p333_0","0p667_1_0p333_0","0p667_1_0p333_0"],"t":0,"s":[0,0,100],"e":[100,100,100]},{"t":31}],"ix":6}},"ao":0,"shapes":[{"ty":"gr","it":[{"ind":0,"ty":"sh","ix":1,"ks":{"a":0,"k":{"i":[[-1.175,-4.481],[1.175,4.481],[-4.651,1.219]],"o":[[1.175,4.482],[-1.175,-4.482],[4.653,-1.22]],"v":[[9.314,-2.461],[-9.314,3.87],[-1.788,-7.131]],"c":true},"ix":2},"nm":"Path 1","mn":"ADBE Vector Shape - Group","hd":false},{"ty":"fl","c":{"a":0,"k":[1,0.801000019148,0.479000016755,1],"ix":4},"o":{"a":0,"k":100,"ix":5},"r":1,"nm":"Fill 1","mn":"ADBE Vector Graphic - Fill","hd":false},{"ty":"tr","p":{"a":0,"k":[10.739,8.601],"ix":2},"a":{"a":0,"k":[0,0],"ix":1},"s":{"a":0,"k":[100,100],"ix":3},"r":{"a":0,"k":0,"ix":6},"o":{"a":0,"k":100,"ix":7},"sk":{"a":0,"k":0,"ix":4},"sa":{"a":0,"k":0,"ix":5},"nm":"Transform"}],"nm":"Group 1","np":2,"cix":2,"ix":1,"mn":"ADBE Vector Group","hd":false}],"ip":0,"op":205,"st":0,"bm":0},{"ddd":0,"ind":2,"ty":4,"nm":"petal1","sr":1,"ks":{"o":{"a":0,"k":100,"ix":11},"r":{"a":1,"k":[{"i":{"x":[0.667],"y":[1]},"o":{"x":[0.333],"y":[0]},"n":["0p667_1_0p333_0"],"t":5.2,"s":[0],"e":[7]},{"i":{"x":[0.667],"y":[1]},"o":{"x":[0.333],"y":[0]},"n":["0p667_1_0p333_0"],"t":45.001,"s":[7],"e":[-7]},{"i":{"x":[0.667],"y":[1]},"o":{"x":[0.333],"y":[0]},"n":["0p667_1_0p333_0"],"t":92.913,"s":[-7],"e":[7]},{"i":{"x":[0.667],"y":[1]},"o":{"x":[0.333],"y":[0]},"n":["0p667_1_0p333_0"],"t":150.001,"s":[7],"e":[-7]},{"t":197.287890625}],"ix":10},"p":{"a":0,"k":[56.69,54.758,0],"ix":2},"a":{"a":0,"k":[1.225,13.277,0],"ix":1},"s":{"a":1,"k":[{"i":{"x":[0.667,0.667,0.667],"y":[1,1,1]},"o":{"x":[0.333,0.333,0.333],"y":[0,0,0]},"n":["0p667_1_0p333_0","0p667_1_0p333_0","0p667_1_0p333_0"],"t":0.001,"s":[0,0,100],"e":[100,100,100]},{"t":30.00078125}],"ix":6}},"ao":0,"shapes":[{"ty":"gr","it":[{"ind":0,"ty":"sh","ix":1,"ks":{"a":0,"k":{"i":[[-1.583,3.076],[-9.319,2.132],[-1.369,-5.254],[14.805,0.9]],"o":[[1.487,-2.889],[12.654,-2.896],[1.694,6.503],[-10.273,-0.625]],"v":[[-23.142,4.663],[-2.721,-5.131],[23.031,-2.649],[1.111,7.127]],"c":true},"ix":2},"nm":"Path 1","mn":"ADBE Vector Shape - Group","hd":false},{"ty":"fl","c":{"a":0,"k":[1,1,1,1],"ix":4},"o":{"a":0,"k":100,"ix":5},"r":1,"nm":"Fill 1","mn":"ADBE Vector Graphic - Fill","hd":false},{"ty":"tr","p":{"a":0,"k":[24.975,8.277],"ix":2},"a":{"a":0,"k":[0,0],"ix":1},"s":{"a":0,"k":[100,100],"ix":3},"r":{"a":0,"k":0,"ix":6},"o":{"a":0,"k":100,"ix":7},"sk":{"a":0,"k":0,"ix":4},"sa":{"a":0,"k":0,"ix":5},"nm":"Transform"}],"nm":"Group 1","np":2,"cix":2,"ix":1,"mn":"ADBE Vector Group","hd":false}],"ip":0,"op":205,"st":-4.8,"bm":0},{"ddd":0,"ind":3,"ty":4,"nm":"petal2","sr":1,"ks":{"o":{"a":0,"k":100,"ix":11},"r":{"a":1,"k":[{"i":{"x":[0.667],"y":[1]},"o":{"x":[0.333],"y":[0]},"n":["0p667_1_0p333_0"],"t":5.2,"s":[0],"e":[7]},{"i":{"x":[0.667],"y":[1]},"o":{"x":[0.333],"y":[0]},"n":["0p667_1_0p333_0"],"t":45.2,"s":[7],"e":[-7]},{"i":{"x":[0.667],"y":[1]},"o":{"x":[0.333],"y":[0]},"n":["0p667_1_0p333_0"],"t":92.913,"s":[-7],"e":[7]},{"i":{"x":[0.667],"y":[1]},"o":{"x":[0.333],"y":[0]},"n":["0p667_1_0p333_0"],"t":149.001,"s":[7],"e":[-7]},{"t":197.287890625}],"ix":10},"p":{"a":0,"k":[56.646,54.278,0],"ix":2},"a":{"a":0,"k":[2.177,0.91,0],"ix":1},"s":{"a":1,"k":[{"i":{"x":[0.667,0.667,0.667],"y":[1,1,1]},"o":{"x":[0.333,0.333,0.333],"y":[0,0,0]},"n":["0p667_1_0p333_0","0p667_1_0p333_0","0p667_1_0p333_0"],"t":0.001,"s":[0,0,100],"e":[100,100,100]},{"t":30.00078125}],"ix":6}},"ao":0,"shapes":[{"ty":"gr","it":[{"ind":0,"ty":"sh","ix":1,"ks":{"a":0,"k":{"i":[[-2.878,1.921],[-10.07,-3.905],[2.41,-4.864],[10.618,6.677]],"o":[[3.055,-2.039],[12.103,4.692],[-2.983,6.022],[-8.712,-5.479]],"v":[[-20.799,-12.371],[5.042,-9.206],[21.267,8.387],[-3.569,5.588]],"c":true},"ix":2},"nm":"Path 1","mn":"ADBE Vector Shape - Group","hd":false},{"ty":"fl","c":{"a":0,"k":[1,1,1,1],"ix":4},"o":{"a":0,"k":100,"ix":5},"r":1,"nm":"Fill 1","mn":"ADBE Vector Graphic - Fill","hd":false},{"ty":"tr","p":{"a":0,"k":[23.927,14.66],"ix":2},"a":{"a":0,"k":[0,0],"ix":1},"s":{"a":0,"k":[100,100],"ix":3},"r":{"a":0,"k":0,"ix":6},"o":{"a":0,"k":100,"ix":7},"sk":{"a":0,"k":0,"ix":4},"sa":{"a":0,"k":0,"ix":5},"nm":"Transform"}],"nm":"Group 1","np":2,"cix":2,"ix":1,"mn":"ADBE Vector Group","hd":false}],"ip":0,"op":205,"st":-4.8,"bm":0},{"ddd":0,"ind":4,"ty":4,"nm":"petal3","sr":1,"ks":{"o":{"a":0,"k":100,"ix":11},"r":{"a":1,"k":[{"i":{"x":[0.667],"y":[1]},"o":{"x":[0.333],"y":[0]},"n":["0p667_1_0p333_0"],"t":7.6,"s":[0],"e":[7]},{"i":{"x":[0.667],"y":[1]},"o":{"x":[0.333],"y":[0]},"n":["0p667_1_0p333_0"],"t":48,"s":[7],"e":[-7]},{"i":{"x":[0.667],"y":[1]},"o":{"x":[0.333],"y":[0]},"n":["0p667_1_0p333_0"],"t":95.313,"s":[-7],"e":[7]},{"i":{"x":[0.667],"y":[1]},"o":{"x":[0.333],"y":[0]},"n":["0p667_1_0p333_0"],"t":152,"s":[7],"e":[-7]},{"t":199.687890625}],"ix":10},"p":{"a":0,"k":[56.463,56.337,0],"ix":2},"a":{"a":0,"k":[3.482,1.362,0],"ix":1},"s":{"a":1,"k":[{"i":{"x":[0.667,0.667,0.667],"y":[1,1,1]},"o":{"x":[0.333,0.333,0.333],"y":[0,0,0]},"n":["0p667_1_0p333_0","0p667_1_0p333_0","0p667_1_0p333_0"],"t":0,"s":[0,0,100],"e":[100,100,100]},{"t":30.000390625}],"ix":6}},"ao":0,"shapes":[{"ty":"gr","it":[{"ind":0,"ty":"sh","ix":1,"ks":{"a":0,"k":{"i":[[-3.316,0.985],[-3.863,-8.745],[4.907,-2.322],[2.711,12.367]],"o":[[3.425,-1.018],[4.63,10.478],[-6.075,2.875],[-2.203,-10.054]],"v":[[-9.121,-21.344],[8.102,-1.002],[6.281,19.487],[-10.529,3.505]],"c":true},"ix":2},"nm":"Path 1","mn":"ADBE Vector Shape - Group","hd":false},{"ty":"fl","c":{"a":0,"k":[1,1,1,1],"ix":4},"o":{"a":0,"k":100,"ix":5},"r":1,"nm":"Fill 1","mn":"ADBE Vector Graphic - Fill","hd":false},{"ty":"tr","p":{"a":0,"k":[12.982,22.612],"ix":2},"a":{"a":0,"k":[0,0],"ix":1},"s":{"a":0,"k":[100,100],"ix":3},"r":{"a":0,"k":0,"ix":6},"o":{"a":0,"k":100,"ix":7},"sk":{"a":0,"k":0,"ix":4},"sa":{"a":0,"k":0,"ix":5},"nm":"Transform"}],"nm":"Group 1","np":2,"cix":2,"ix":1,"mn":"ADBE Vector Group","hd":false}],"ip":0,"op":205,"st":-2.4,"bm":0},{"ddd":0,"ind":5,"ty":4,"nm":"petal4","sr":1,"ks":{"o":{"a":0,"k":100,"ix":11},"r":{"a":1,"k":[{"i":{"x":[0.667],"y":[1]},"o":{"x":[0.333],"y":[0]},"n":["0p667_1_0p333_0"],"t":5.2,"s":[0],"e":[7]},{"i":{"x":[0.667],"y":[1]},"o":{"x":[0.333],"y":[0]},"n":["0p667_1_0p333_0"],"t":45.2,"s":[7],"e":[-7]},{"i":{"x":[0.667],"y":[1]},"o":{"x":[0.333],"y":[0]},"n":["0p667_1_0p333_0"],"t":92.913,"s":[-7],"e":[7]},{"i":{"x":[0.667],"y":[1]},"o":{"x":[0.333],"y":[0]},"n":["0p667_1_0p333_0"],"t":149.001,"s":[7],"e":[-7]},{"t":197.287890625}],"ix":10},"p":{"a":0,"k":[53.564,57.405,0],"ix":2},"a":{"a":0,"k":[19.169,1.573,0],"ix":1},"s":{"a":1,"k":[{"i":{"x":[0.667,0.667,0.667],"y":[1,1,1]},"o":{"x":[0.333,0.333,0.333],"y":[0,0,0]},"n":["0p667_1_0p333_0","0p667_1_0p333_0","0p667_1_0p333_0"],"t":0.001,"s":[0,0,100],"e":[100,100,100]},{"t":30.00078125}],"ix":6}},"ao":0,"shapes":[{"ty":"gr","it":[{"ind":0,"ty":"sh","ix":1,"ks":{"a":0,"k":{"i":[[-3.305,-1.025],[1.687,-9.41],[5.37,0.798],[-4.965,11.652]],"o":[[3.413,1.059],[-2.291,12.778],[-6.648,-0.987],[3.897,-9.149]],"v":[[8.257,-22.048],[9.12,1.936],[-3.341,22.275],[-6.704,-0.532]],"c":true},"ix":2},"nm":"Path 1","mn":"ADBE Vector Shape - Group","hd":false},{"ty":"fl","c":{"a":0,"k":[1,1,1,1],"ix":4},"o":{"a":0,"k":100,"ix":5},"r":1,"nm":"Fill 1","mn":"ADBE Vector Graphic - Fill","hd":false},{"ty":"tr","p":{"a":0,"k":[11.919,23.323],"ix":2},"a":{"a":0,"k":[0,0],"ix":1},"s":{"a":0,"k":[100,100],"ix":3},"r":{"a":0,"k":0,"ix":6},"o":{"a":0,"k":100,"ix":7},"sk":{"a":0,"k":0,"ix":4},"sa":{"a":0,"k":0,"ix":5},"nm":"Transform"}],"nm":"Group 1","np":2,"cix":2,"ix":1,"mn":"ADBE Vector Group","hd":false}],"ip":0,"op":205,"st":-4.8,"bm":0},{"ddd":0,"ind":6,"ty":4,"nm":"petal5","sr":1,"ks":{"o":{"a":0,"k":100,"ix":11},"r":{"a":1,"k":[{"i":{"x":[0.667],"y":[1]},"o":{"x":[0.333],"y":[0]},"n":["0p667_1_0p333_0"],"t":-3.4,"s":[0],"e":[7]},{"i":{"x":[0.667],"y":[1]},"o":{"x":[0.333],"y":[0]},"n":["0p667_1_0p333_0"],"t":36,"s":[7],"e":[-7]},{"i":{"x":[0.667],"y":[1]},"o":{"x":[0.333],"y":[0]},"n":["0p667_1_0p333_0"],"t":84.313,"s":[-7],"e":[7]},{"i":{"x":[0.667],"y":[1]},"o":{"x":[0.333],"y":[0]},"n":["0p667_1_0p333_0"],"t":141,"s":[7],"e":[-7]},{"t":188.687890625}],"ix":10},"p":{"a":0,"k":[57.328,55.577,0],"ix":2},"a":{"a":0,"k":[41.905,3.041,0],"ix":1},"s":{"a":1,"k":[{"i":{"x":[0.667,0.667,0.667],"y":[1,1,1]},"o":{"x":[0.333,0.333,0.333],"y":[0,0,0]},"n":["0p667_1_0p333_0","0p667_1_0p333_0","0p667_1_0p333_0"],"t":0,"s":[0,0,100],"e":[100,100,100]},{"t":30.000390625}],"ix":6}},"ao":0,"shapes":[{"ty":"gr","it":[{"ind":0,"ty":"sh","ix":1,"ks":{"a":0,"k":{"i":[[-0.15,-3.457],[6.294,-7.194],[3.793,3.883],[-10.244,7.451]],"o":[[0.141,3.246],[-9.455,10.808],[-4.695,-4.808],[8.322,-6.055]],"v":[[20.514,-14.834],[6.057,2.736],[-15.96,14.408],[-2.176,-6.733]],"c":true},"ix":2},"nm":"Path 1","mn":"ADBE Vector Shape - Group","hd":false},{"ty":"fl","c":{"a":0,"k":[1,1,1,1],"ix":4},"o":{"a":0,"k":100,"ix":5},"r":1,"nm":"Fill 1","mn":"ADBE Vector Graphic - Fill","hd":false},{"ty":"tr","p":{"a":0,"k":[20.905,18.541],"ix":2},"a":{"a":0,"k":[0,0],"ix":1},"s":{"a":0,"k":[100,100],"ix":3},"r":{"a":0,"k":0,"ix":6},"o":{"a":0,"k":100,"ix":7},"sk":{"a":0,"k":0,"ix":4},"sa":{"a":0,"k":0,"ix":5},"nm":"Transform"}],"nm":"Group 1","np":2,"cix":2,"ix":1,"mn":"ADBE Vector Group","hd":false}],"ip":-11,"op":207,"st":-13.4,"bm":0}]},{"id":"comp_2","layers":[{"ddd":0,"ind":1,"ty":0,"nm":"whiteflower whole","parent":3,"refId":"comp_3","sr":1,"ks":{"o":{"a":0,"k":100,"ix":11},"r":{"a":0,"k":0,"ix":10},"p":{"a":0,"k":[41.988,3.077,0],"ix":2},"a":{"a":0,"k":[57.5,57.5,0],"ix":1},"s":{"a":0,"k":[100,100,100],"ix":6}},"ao":0,"w":115,"h":115,"ip":54,"op":258,"st":54,"bm":0},{"ddd":0,"ind":2,"ty":4,"nm":"flower bud 1","parent":3,"sr":1,"ks":{"o":{"a":0,"k":100,"ix":11},"r":{"a":1,"k":[{"i":{"x":[0.667],"y":[1]},"o":{"x":[0.333],"y":[0]},"n":["0p667_1_0p333_0"],"t":61,"s":[0],"e":[70]},{"t":62}],"ix":10},"p":{"a":1,"k":[{"i":{"x":0.667,"y":1},"o":{"x":0.333,"y":0},"n":"0p667_1_0p333_0","t":0,"s":[31.103,169.521,0],"e":[38.693,5.577,0],"to":[0,0,0],"ti":[-33.7050018310547,82.5370178222656,0]},{"t":61}],"ix":2},"a":{"a":0,"k":[19.784,-61.88,0],"ix":1},"s":{"a":1,"k":[{"i":{"x":[0.667,0.667,0.667],"y":[1,1,1]},"o":{"x":[0.333,0.333,0.333],"y":[0,0,0]},"n":["0p667_1_0p333_0","0p667_1_0p333_0","0p667_1_0p333_0"],"t":20,"s":[0,0,100],"e":[60,60,100]},{"t":61}],"ix":6}},"ao":0,"shapes":[{"ty":"gr","it":[{"ind":0,"ty":"sh","ix":1,"ks":{"a":0,"k":{"i":[[2.75,1.75],[-4.25,-3.25]],"o":[[-2.75,-1.75],[4.25,3.25]],"v":[[25.75,-74.5],[19.5,-62.25]],"c":true},"ix":2},"nm":"Path 1","mn":"ADBE Vector Shape - Group","hd":false},{"ty":"fl","c":{"a":0,"k":[1,1,1,1],"ix":4},"o":{"a":0,"k":100,"ix":5},"r":1,"nm":"Fill 1","mn":"ADBE Vector Graphic - Fill","hd":false},{"ty":"tr","p":{"a":0,"k":[0,0],"ix":2},"a":{"a":0,"k":[0,0],"ix":1},"s":{"a":0,"k":[100,100],"ix":3},"r":{"a":0,"k":0,"ix":6},"o":{"a":0,"k":100,"ix":7},"sk":{"a":0,"k":0,"ix":4},"sa":{"a":0,"k":0,"ix":5},"nm":"Transform"}],"nm":"Shape 1","np":3,"cix":2,"ix":1,"mn":"ADBE Vector Group","hd":false}],"ip":0,"op":337,"st":0,"bm":0},{"ddd":0,"ind":3,"ty":4,"nm":"scape1","sr":1,"ks":{"o":{"a":0,"k":100,"ix":11},"r":{"a":1,"k":[{"i":{"x":[0.667],"y":[1]},"o":{"x":[0.333],"y":[0]},"n":["0p667_1_0p333_0"],"t":0,"s":[0],"e":[4]},{"i":{"x":[0.667],"y":[1]},"o":{"x":[0.333],"y":[0]},"n":["0p667_1_0p333_0"],"t":61,"s":[4],"e":[-2]},{"i":{"x":[0.667],"y":[1]},"o":{"x":[0.333],"y":[0]},"n":["0p667_1_0p333_0"],"t":120,"s":[-2],"e":[2]},{"i":{"x":[0.667],"y":[1]},"o":{"x":[0.333],"y":[0]},"n":["0p667_1_0p333_0"],"t":181,"s":[2],"e":[-2]},{"t":241}],"ix":10},"p":{"a":0,"k":[161.864,252.645,0],"ix":2},"a":{"a":0,"k":[30.853,169.222,0],"ix":1},"s":{"a":0,"k":[100,100,100],"ix":6}},"ao":0,"shapes":[{"ty":"gr","it":[{"ind":0,"ty":"sh","ix":1,"ks":{"a":0,"k":{"i":[[0,0],[-33.705,82.537]],"o":[[0,0],[0,0]],"v":[[9.263,81.972],[16.853,-81.972]],"c":false},"ix":2},"nm":"Path 1","mn":"ADBE Vector Shape - Group","hd":false},{"ty":"st","c":{"a":0,"k":[0.311000001197,0.119999994016,0.215000002992,1],"ix":3},"o":{"a":0,"k":100,"ix":4},"w":{"a":0,"k":1.1,"ix":5},"lc":2,"lj":1,"ml":10,"nm":"Stroke 1","mn":"ADBE Vector Graphic - Stroke","hd":false},{"ty":"tr","p":{"a":0,"k":[21.853,86.972],"ix":2},"a":{"a":0,"k":[0,0],"ix":1},"s":{"a":0,"k":[100,100],"ix":3},"r":{"a":0,"k":0,"ix":6},"o":{"a":0,"k":100,"ix":7},"sk":{"a":0,"k":0,"ix":4},"sa":{"a":0,"k":0,"ix":5},"nm":"Transform"}],"nm":"Group 1","np":2,"cix":2,"ix":1,"mn":"ADBE Vector Group","hd":false},{"ty":"tm","s":{"a":0,"k":0,"ix":1},"e":{"a":1,"k":[{"i":{"x":[0.667],"y":[1]},"o":{"x":[0.333],"y":[0]},"n":["0p667_1_0p333_0"],"t":0,"s":[0],"e":[100]},{"t":61}],"ix":2},"o":{"a":0,"k":0,"ix":3},"m":1,"ix":2,"nm":"Trim Paths 1","mn":"ADBE Vector Filter - Trim","hd":false}],"ip":0,"op":337,"st":0,"bm":0}]},{"id":"comp_3","layers":[{"ddd":0,"ind":1,"ty":4,"nm":"pistil","sr":1,"ks":{"o":{"a":0,"k":100,"ix":11},"r":{"a":0,"k":0,"ix":10},"p":{"a":0,"k":[55.401,58.793,0],"ix":2},"a":{"a":0,"k":[11.676,11.676,0],"ix":1},"s":{"a":1,"k":[{"i":{"x":[0.667,0.667,0.667],"y":[1,1,1]},"o":{"x":[0.333,0.333,0.333],"y":[0,0,0]},"n":["0p667_1_0p333_0","0p667_1_0p333_0","0p667_1_0p333_0"],"t":0,"s":[0,0,100],"e":[100,100,100]},{"t":30}],"ix":6}},"ao":0,"shapes":[{"ty":"gr","it":[{"ind":0,"ty":"sh","ix":1,"ks":{"a":0,"k":{"i":[[0,-6.31],[6.311,0],[0,6.311],[-6.31,0]],"o":[[0,6.311],[-6.31,0],[0,-6.31],[6.311,0]],"v":[[11.426,0],[0,11.426],[-11.426,0],[0,-11.426]],"c":true},"ix":2},"nm":"Path 1","mn":"ADBE Vector Shape - Group","hd":false},{"ty":"fl","c":{"a":0,"k":[1,0.801000019148,0.479000016755,1],"ix":4},"o":{"a":0,"k":100,"ix":5},"r":1,"nm":"Fill 1","mn":"ADBE Vector Graphic - Fill","hd":false},{"ty":"tr","p":{"a":0,"k":[11.676,11.676],"ix":2},"a":{"a":0,"k":[0,0],"ix":1},"s":{"a":0,"k":[100,100],"ix":3},"r":{"a":0,"k":0,"ix":6},"o":{"a":0,"k":100,"ix":7},"sk":{"a":0,"k":0,"ix":4},"sa":{"a":0,"k":0,"ix":5},"nm":"Transform"}],"nm":"Group 1","np":2,"cix":2,"ix":1,"mn":"ADBE Vector Group","hd":false}],"ip":0,"op":222,"st":0,"bm":0},{"ddd":0,"ind":2,"ty":4,"nm":"1","sr":1,"ks":{"o":{"a":0,"k":100,"ix":11},"r":{"a":1,"k":[{"i":{"x":[0.667],"y":[1]},"o":{"x":[0.333],"y":[0]},"n":["0p667_1_0p333_0"],"t":10,"s":[0],"e":[11]},{"i":{"x":[0.667],"y":[1]},"o":{"x":[0.333],"y":[0]},"n":["0p667_1_0p333_0"],"t":50,"s":[11],"e":[-7]},{"i":{"x":[0.667],"y":[1]},"o":{"x":[0.333],"y":[0]},"n":["0p667_1_0p333_0"],"t":97.713,"s":[-7],"e":[11]},{"i":{"x":[0.667],"y":[1]},"o":{"x":[0.333],"y":[0]},"n":["0p667_1_0p333_0"],"t":154.371,"s":[11],"e":[-7]},{"t":202.087890625}],"ix":10},"p":{"a":0,"k":[58.593,57.756,0],"ix":2},"a":{"a":0,"k":[2.985,26.109,0],"ix":1},"s":{"a":1,"k":[{"i":{"x":[0.667,0.667,0.667],"y":[1,1,1]},"o":{"x":[0.333,0.333,0.333],"y":[0,0,0]},"n":["0p667_1_0p333_0","0p667_1_0p333_0","0p667_1_0p333_0"],"t":2,"s":[0,0,100],"e":[100,100,100]},{"t":32}],"ix":6}},"ao":0,"shapes":[{"ty":"gr","it":[{"ind":0,"ty":"sh","ix":1,"ks":{"a":0,"k":{"i":[[1.731,5.129],[-9.02,4.322],[-2.498,-7.313],[14.05,-3.809]],"o":[[-2.011,-5.956],[13.454,-6.447],[2.497,7.309],[-11.416,3.095]],"v":[[-24.723,10.23],[-2.876,-8.913],[24.238,-7.354],[3.434,10.669]],"c":true},"ix":2},"nm":"Path 1","mn":"ADBE Vector Shape - Group","hd":false},{"ty":"fl","c":{"a":0,"k":[1,1,1,1],"ix":4},"o":{"a":0,"k":100,"ix":5},"r":1,"nm":"Fill 1","mn":"ADBE Vector Graphic - Fill","hd":false},{"ty":"tr","p":{"a":0,"k":[26.984,15.61],"ix":2},"a":{"a":0,"k":[0,0],"ix":1},"s":{"a":0,"k":[100,100],"ix":3},"r":{"a":0,"k":0,"ix":6},"o":{"a":0,"k":100,"ix":7},"sk":{"a":0,"k":0,"ix":4},"sa":{"a":0,"k":0,"ix":5},"nm":"Transform"}],"nm":"Group 1","np":2,"cix":2,"ix":1,"mn":"ADBE Vector Group","hd":false}],"ip":0,"op":222,"st":0,"bm":0},{"ddd":0,"ind":3,"ty":4,"nm":"2","sr":1,"ks":{"o":{"a":0,"k":100,"ix":11},"r":{"a":1,"k":[{"i":{"x":[0.667],"y":[1]},"o":{"x":[0.333],"y":[0]},"n":["0p667_1_0p333_0"],"t":7,"s":[0],"e":[11]},{"i":{"x":[0.667],"y":[1]},"o":{"x":[0.333],"y":[0]},"n":["0p667_1_0p333_0"],"t":37.088,"s":[11],"e":[-7]},{"i":{"x":[0.667],"y":[1]},"o":{"x":[0.333],"y":[0]},"n":["0p667_1_0p333_0"],"t":84.801,"s":[-7],"e":[11]},{"i":{"x":[0.667],"y":[1]},"o":{"x":[0.333],"y":[0]},"n":["0p667_1_0p333_0"],"t":141.463,"s":[11],"e":[-7]},{"t":189.17578125}],"ix":10},"p":{"a":0,"k":[57.313,58.193,0],"ix":2},"a":{"a":0,"k":[2.797,4.643,0],"ix":1},"s":{"a":1,"k":[{"i":{"x":[0.667,0.667,0.667],"y":[1,1,1]},"o":{"x":[0.333,0.333,0.333],"y":[0,0,0]},"n":["0p667_1_0p333_0","0p667_1_0p333_0","0p667_1_0p333_0"],"t":2,"s":[0,0,100],"e":[100,100,100]},{"t":32}],"ix":6}},"ao":0,"shapes":[{"ty":"gr","it":[{"ind":0,"ty":"sh","ix":1,"ks":{"a":0,"k":{"i":[[-2.707,4.688],[-9.203,-3.915],[3.84,-6.706],[12.141,8.031]],"o":[[3.143,-5.444],[13.727,5.841],[-3.838,6.703],[-9.865,-6.525]],"v":[[-23.34,-13.199],[5.464,-9.446],[22.207,11.939],[-5.067,8.229]],"c":true},"ix":2},"nm":"Path 1","mn":"ADBE Vector Shape - Group","hd":false},{"ty":"fl","c":{"a":0,"k":[1,1,1,1],"ix":4},"o":{"a":0,"k":100,"ix":5},"r":1,"nm":"Fill 1","mn":"ADBE Vector Graphic - Fill","hd":false},{"ty":"tr","p":{"a":0,"k":[26.297,18.893],"ix":2},"a":{"a":0,"k":[0,0],"ix":1},"s":{"a":0,"k":[100,100],"ix":3},"r":{"a":0,"k":0,"ix":6},"o":{"a":0,"k":100,"ix":7},"sk":{"a":0,"k":0,"ix":4},"sa":{"a":0,"k":0,"ix":5},"nm":"Transform"}],"nm":"Group 1","np":2,"cix":2,"ix":1,"mn":"ADBE Vector Group","hd":false}],"ip":-3,"op":219,"st":-3,"bm":0},{"ddd":0,"ind":4,"ty":4,"nm":"3","sr":1,"ks":{"o":{"a":0,"k":100,"ix":11},"r":{"a":1,"k":[{"i":{"x":[0.667],"y":[1]},"o":{"x":[0.333],"y":[0]},"n":["0p667_1_0p333_0"],"t":9,"s":[0],"e":[11]},{"i":{"x":[0.667],"y":[1]},"o":{"x":[0.333],"y":[0]},"n":["0p667_1_0p333_0"],"t":47.016,"s":[11],"e":[-7]},{"i":{"x":[0.667],"y":[1]},"o":{"x":[0.333],"y":[0]},"n":["0p667_1_0p333_0"],"t":94.73,"s":[-7],"e":[11]},{"i":{"x":[0.667],"y":[1]},"o":{"x":[0.333],"y":[0]},"n":["0p667_1_0p333_0"],"t":151.391,"s":[11],"e":[-7]},{"t":199.103515625}],"ix":10},"p":{"a":0,"k":[55.499,58.958,0],"ix":2},"a":{"a":0,"k":[5.888,1.069,0],"ix":1},"s":{"a":1,"k":[{"i":{"x":[0.667,0.667,0.667],"y":[1,1,1]},"o":{"x":[0.333,0.333,0.333],"y":[0,0,0]},"n":["0p667_1_0p333_0","0p667_1_0p333_0","0p667_1_0p333_0"],"t":2,"s":[0,0,100],"e":[100,100,100]},{"t":32}],"ix":6}},"ao":0,"shapes":[{"ty":"gr","it":[{"ind":0,"ty":"sh","ix":1,"ks":{"a":0,"k":{"i":[[-5.238,1.365],[-3.676,-9.303],[7.471,-1.975],[2.809,14.283]],"o":[[6.083,-1.585],[5.482,13.875],[-7.468,1.975],[-2.282,-11.606]],"v":[[-8.9,-25.235],[8.656,-2.092],[5.189,24.845],[-11.322,2.823]],"c":true},"ix":2},"nm":"Path 1","mn":"ADBE Vector Shape - Group","hd":false},{"ty":"fl","c":{"a":0,"k":[1,1,1,1],"ix":4},"o":{"a":0,"k":100,"ix":5},"r":1,"nm":"Fill 1","mn":"ADBE Vector Graphic - Fill","hd":false},{"ty":"tr","p":{"a":0,"k":[14.388,27.069],"ix":2},"a":{"a":0,"k":[0,0],"ix":1},"s":{"a":0,"k":[100,100],"ix":3},"r":{"a":0,"k":0,"ix":6},"o":{"a":0,"k":100,"ix":7},"sk":{"a":0,"k":0,"ix":4},"sa":{"a":0,"k":0,"ix":5},"nm":"Transform"}],"nm":"Group 1","np":2,"cix":2,"ix":1,"mn":"ADBE Vector Group","hd":false}],"ip":-1,"op":221,"st":-1,"bm":0},{"ddd":0,"ind":5,"ty":4,"nm":"4","sr":1,"ks":{"o":{"a":0,"k":100,"ix":11},"r":{"a":1,"k":[{"i":{"x":[0.667],"y":[1]},"o":{"x":[0.333],"y":[0]},"n":["0p667_1_0p333_0"],"t":8,"s":[0],"e":[11]},{"i":{"x":[0.667],"y":[1]},"o":{"x":[0.333],"y":[0]},"n":["0p667_1_0p333_0"],"t":44.035,"s":[11],"e":[-7]},{"i":{"x":[0.667],"y":[1]},"o":{"x":[0.333],"y":[0]},"n":["0p667_1_0p333_0"],"t":91.75,"s":[-7],"e":[11]},{"i":{"x":[0.667],"y":[1]},"o":{"x":[0.333],"y":[0]},"n":["0p667_1_0p333_0"],"t":148.406,"s":[11],"e":[-7]},{"t":196.123046875}],"ix":10},"p":{"a":0,"k":[54.965,58.296,0],"ix":2},"a":{"a":0,"k":[37.434,2.475,0],"ix":1},"s":{"a":1,"k":[{"i":{"x":[0.667,0.667,0.667],"y":[1,1,1]},"o":{"x":[0.333,0.333,0.333],"y":[0,0,0]},"n":["0p667_1_0p333_0","0p667_1_0p333_0","0p667_1_0p333_0"],"t":2,"s":[0,0,100],"e":[100,100,100]},{"t":32}],"ix":6}},"ao":0,"shapes":[{"ty":"gr","it":[{"ind":0,"ty":"sh","ix":1,"ks":{"a":0,"k":{"i":[[-4.151,-3.474],[5.441,-8.393],[5.945,4.937],[-10.001,10.577]],"o":[[4.822,4.033],[-8.117,12.517],[-5.942,-4.934],[8.127,-8.594]],"v":[[16.862,-21.001],[8.206,6.728],[-15.742,19.538],[-7.391,-6.689]],"c":true},"ix":2},"nm":"Path 1","mn":"ADBE Vector Shape - Group","hd":false},{"ty":"fl","c":{"a":0,"k":[1,1,1,1],"ix":4},"o":{"a":0,"k":100,"ix":5},"r":1,"nm":"Fill 1","mn":"ADBE Vector Graphic - Fill","hd":false},{"ty":"tr","p":{"a":0,"k":[21.934,24.725],"ix":2},"a":{"a":0,"k":[0,0],"ix":1},"s":{"a":0,"k":[100,100],"ix":3},"r":{"a":0,"k":0,"ix":6},"o":{"a":0,"k":100,"ix":7},"sk":{"a":0,"k":0,"ix":4},"sa":{"a":0,"k":0,"ix":5},"nm":"Transform"}],"nm":"Group 1","np":2,"cix":2,"ix":1,"mn":"ADBE Vector Group","hd":false}],"ip":-2,"op":220,"st":-2,"bm":0},{"ddd":0,"ind":6,"ty":4,"nm":"5","sr":1,"ks":{"o":{"a":0,"k":100,"ix":11},"r":{"a":1,"k":[{"i":{"x":[0.667],"y":[1]},"o":{"x":[0.333],"y":[0]},"n":["0p667_1_0p333_0"],"t":7,"s":[0],"e":[11]},{"i":{"x":[0.667],"y":[1]},"o":{"x":[0.333],"y":[0]},"n":["0p667_1_0p333_0"],"t":41.053,"s":[11],"e":[-7]},{"i":{"x":[0.667],"y":[1]},"o":{"x":[0.333],"y":[0]},"n":["0p667_1_0p333_0"],"t":88.766,"s":[-7],"e":[11]},{"i":{"x":[0.667],"y":[1]},"o":{"x":[0.333],"y":[0]},"n":["0p667_1_0p333_0"],"t":145.426,"s":[11],"e":[-7]},{"t":193.140625}],"ix":10},"p":{"a":0,"k":[51.217,60.688,0],"ix":2},"a":{"a":0,"k":[50.056,10.672,0],"ix":1},"s":{"a":1,"k":[{"i":{"x":[0.667,0.667,0.667],"y":[1,1,1]},"o":{"x":[0.333,0.333,0.333],"y":[0,0,0]},"n":["0p667_1_0p333_0","0p667_1_0p333_0","0p667_1_0p333_0"],"t":2,"s":[0,0,100],"e":[100,100,100]},{"t":32}],"ix":6}},"ao":0,"shapes":[{"ty":"gr","it":[{"ind":0,"ty":"sh","ix":1,"ks":{"a":0,"k":{"i":[[-0.563,-5.384],[9.748,-2.239],[0.832,7.683],[-14.542,0.635]],"o":[[0.655,6.252],[-14.54,3.339],[-0.833,-7.679],[11.817,-0.515]],"v":[[25.902,-5.053],[0.387,8.833],[-25.723,1.365],[-1.475,-11.657]],"c":true},"ix":2},"nm":"Path 1","mn":"ADBE Vector Shape - Group","hd":false},{"ty":"fl","c":{"a":0,"k":[1,1,1,1],"ix":4},"o":{"a":0,"k":100,"ix":5},"r":1,"nm":"Fill 1","mn":"ADBE Vector Graphic - Fill","hd":false},{"ty":"tr","p":{"a":0,"k":[26.806,12.422],"ix":2},"a":{"a":0,"k":[0,0],"ix":1},"s":{"a":0,"k":[100,100],"ix":3},"r":{"a":0,"k":0,"ix":6},"o":{"a":0,"k":100,"ix":7},"sk":{"a":0,"k":0,"ix":4},"sa":{"a":0,"k":0,"ix":5},"nm":"Transform"}],"nm":"Group 1","np":2,"cix":2,"ix":1,"mn":"ADBE Vector Group","hd":false}],"ip":-3,"op":219,"st":-3,"bm":0},{"ddd":0,"ind":7,"ty":4,"nm":"6","sr":1,"ks":{"o":{"a":0,"k":100,"ix":11},"r":{"a":1,"k":[{"i":{"x":[0.667],"y":[1]},"o":{"x":[0.333],"y":[0]},"n":["0p667_1_0p333_0"],"t":9,"s":[0],"e":[11]},{"i":{"x":[0.667],"y":[1]},"o":{"x":[0.333],"y":[0]},"n":["0p667_1_0p333_0"],"t":47.016,"s":[11],"e":[-7]},{"i":{"x":[0.667],"y":[1]},"o":{"x":[0.333],"y":[0]},"n":["0p667_1_0p333_0"],"t":94.73,"s":[-7],"e":[11]},{"i":{"x":[0.667],"y":[1]},"o":{"x":[0.333],"y":[0]},"n":["0p667_1_0p333_0"],"t":151.391,"s":[11],"e":[-7]},{"t":199.103515625}],"ix":10},"p":{"a":0,"k":[53.897,57.634,0],"ix":2},"a":{"a":0,"k":[40.375,44.114,0],"ix":1},"s":{"a":1,"k":[{"i":{"x":[0.667,0.667,0.667],"y":[1,1,1]},"o":{"x":[0.333,0.333,0.333],"y":[0,0,0]},"n":["0p667_1_0p333_0","0p667_1_0p333_0","0p667_1_0p333_0"],"t":2,"s":[0,0,100],"e":[100,100,100]},{"t":32}],"ix":6}},"ao":0,"shapes":[{"ty":"gr","it":[{"ind":0,"ty":"sh","ix":1,"ks":{"a":0,"k":{"i":[[4.147,-3.48],[7.309,6.827],[-5.902,4.989],[-8.662,-11.699]],"o":[[-4.815,4.041],[-10.903,-10.183],[5.899,-4.987],[7.038,9.506]],"v":[[17.979,20.073],[-7.805,6.694],[-16.224,-19.127],[8.136,-6.312]],"c":true},"ix":2},"nm":"Path 1","mn":"ADBE Vector Shape - Group","hd":false},{"ty":"fl","c":{"a":0,"k":[1,1,1,1],"ix":4},"o":{"a":0,"k":100,"ix":5},"r":1,"nm":"Fill 1","mn":"ADBE Vector Graphic - Fill","hd":false},{"ty":"tr","p":{"a":0,"k":[22.375,24.364],"ix":2},"a":{"a":0,"k":[0,0],"ix":1},"s":{"a":0,"k":[100,100],"ix":3},"r":{"a":0,"k":0,"ix":6},"o":{"a":0,"k":100,"ix":7},"sk":{"a":0,"k":0,"ix":4},"sa":{"a":0,"k":0,"ix":5},"nm":"Transform"}],"nm":"Group 1","np":2,"cix":2,"ix":1,"mn":"ADBE Vector Group","hd":false}],"ip":-1,"op":221,"st":-1,"bm":0},{"ddd":0,"ind":8,"ty":4,"nm":"7","sr":1,"ks":{"o":{"a":0,"k":100,"ix":11},"r":{"a":1,"k":[{"i":{"x":[0.667],"y":[1]},"o":{"x":[0.333],"y":[0]},"n":["0p667_1_0p333_0"],"t":7,"s":[0],"e":[11]},{"i":{"x":[0.667],"y":[1]},"o":{"x":[0.333],"y":[0]},"n":["0p667_1_0p333_0"],"t":41.053,"s":[11],"e":[-7]},{"i":{"x":[0.667],"y":[1]},"o":{"x":[0.333],"y":[0]},"n":["0p667_1_0p333_0"],"t":88.766,"s":[-7],"e":[11]},{"i":{"x":[0.667],"y":[1]},"o":{"x":[0.333],"y":[0]},"n":["0p667_1_0p333_0"],"t":145.426,"s":[11],"e":[-7]},{"t":193.140625}],"ix":10},"p":{"a":0,"k":[55.069,58.428,0],"ix":2},"a":{"a":0,"k":[6.638,51.378,0],"ix":1},"s":{"a":1,"k":[{"i":{"x":[0.667,0.667,0.667],"y":[1,1,1]},"o":{"x":[0.333,0.333,0.333],"y":[0,0,0]},"n":["0p667_1_0p333_0","0p667_1_0p333_0","0p667_1_0p333_0"],"t":2,"s":[0,0,100],"e":[100,100,100]},{"t":32}],"ix":6}},"ao":0,"shapes":[{"ty":"gr","it":[{"ind":0,"ty":"sh","ix":1,"ks":{"a":0,"k":{"i":[[5.117,1.767],[-2.095,9.78],[-7.314,-2.495],[5.578,-13.446]],"o":[[-5.942,-2.051],[3.125,-14.588],[7.311,2.494],[-4.531,10.926]],"v":[[-8.696,25.111],[-10.485,-3.881],[7.327,-24.383],[8.867,3.098]],"c":true},"ix":2},"nm":"Path 1","mn":"ADBE Vector Shape - Group","hd":false},{"ty":"fl","c":{"a":0,"k":[1,1,1,1],"ix":4},"o":{"a":0,"k":100,"ix":5},"r":1,"nm":"Fill 1","mn":"ADBE Vector Graphic - Fill","hd":false},{"ty":"tr","p":{"a":0,"k":[14.888,27.128],"ix":2},"a":{"a":0,"k":[0,0],"ix":1},"s":{"a":0,"k":[100,100],"ix":3},"r":{"a":0,"k":0,"ix":6},"o":{"a":0,"k":100,"ix":7},"sk":{"a":0,"k":0,"ix":4},"sa":{"a":0,"k":0,"ix":5},"nm":"Transform"}],"nm":"Group 1","np":2,"cix":2,"ix":1,"mn":"ADBE Vector Group","hd":false}],"ip":-3,"op":219,"st":-3,"bm":0}]},{"id":"comp_4","layers":[{"ddd":0,"ind":1,"ty":4,"nm":"3","parent":4,"sr":1,"ks":{"o":{"a":0,"k":100,"ix":11},"r":{"a":0,"k":0.212,"ix":10},"p":{"a":0,"k":[16.854,26.172,0],"ix":2},"a":{"a":0,"k":[0.25,12.035,0],"ix":1},"s":{"a":0,"k":[100,100,100],"ix":6}},"ao":0,"shapes":[{"ty":"gr","it":[{"ind":0,"ty":"sh","ix":1,"ks":{"a":0,"k":{"i":[[0,0],[0,0]],"o":[[0,0],[0,0]],"v":[[0.5,12.071],[0.5,0.5]],"c":false},"ix":2},"nm":"Path 1","mn":"ADBE Vector Shape - Group","hd":false},{"ty":"st","c":{"a":0,"k":[0.311000001197,0.119999994016,0.215000002992,1],"ix":3},"o":{"a":0,"k":100,"ix":4},"w":{"a":0,"k":1,"ix":5},"lc":2,"lj":1,"ml":10,"nm":"Stroke 1","mn":"ADBE Vector Graphic - Stroke","hd":false},{"ty":"tr","p":{"a":0,"k":[0,0],"ix":2},"a":{"a":0,"k":[0,0],"ix":1},"s":{"a":0,"k":[100,100],"ix":3},"r":{"a":0,"k":0,"ix":6},"o":{"a":0,"k":100,"ix":7},"sk":{"a":0,"k":0,"ix":4},"sa":{"a":0,"k":0,"ix":5},"nm":"Transform"}],"nm":"Group 1","np":2,"cix":2,"ix":1,"mn":"ADBE Vector Group","hd":false},{"ty":"tm","s":{"a":0,"k":0,"ix":1},"e":{"a":1,"k":[{"i":{"x":[0.667],"y":[1]},"o":{"x":[0.333],"y":[0]},"n":["0p667_1_0p333_0"],"t":29,"s":[0],"e":[100]},{"t":39}],"ix":2},"o":{"a":0,"k":0,"ix":3},"m":1,"ix":2,"nm":"Trim Paths 1","mn":"ADBE Vector Filter - Trim","hd":false}],"ip":29,"op":366,"st":29,"bm":0},{"ddd":0,"ind":2,"ty":4,"nm":"2","parent":4,"sr":1,"ks":{"o":{"a":0,"k":100,"ix":11},"r":{"a":0,"k":0.212,"ix":10},"p":{"a":0,"k":[11.762,44.75,0],"ix":2},"a":{"a":0,"k":[2.539,12.852,0],"ix":1},"s":{"a":0,"k":[100,100,100],"ix":6}},"ao":0,"shapes":[{"ty":"gr","it":[{"ind":0,"ty":"sh","ix":1,"ks":{"a":0,"k":{"i":[[0,0],[-9.66,3.864]],"o":[[0,0],[0,0]],"v":[[-9.539,5.352],[9.539,-5.352]],"c":false},"ix":2},"nm":"Path 1","mn":"ADBE Vector Shape - Group","hd":false},{"ty":"st","c":{"a":0,"k":[0.311000001197,0.119999994016,0.215000002992,1],"ix":3},"o":{"a":0,"k":100,"ix":4},"w":{"a":0,"k":1,"ix":5},"lc":2,"lj":1,"ml":10,"nm":"Stroke 1","mn":"ADBE Vector Graphic - Stroke","hd":false},{"ty":"tr","p":{"a":0,"k":[12.039,7.852],"ix":2},"a":{"a":0,"k":[0,0],"ix":1},"s":{"a":0,"k":[100,100],"ix":3},"r":{"a":0,"k":0,"ix":6},"o":{"a":0,"k":100,"ix":7},"sk":{"a":0,"k":0,"ix":4},"sa":{"a":0,"k":0,"ix":5},"nm":"Transform"}],"nm":"Group 1","np":2,"cix":2,"ix":1,"mn":"ADBE Vector Group","hd":false},{"ty":"tm","s":{"a":0,"k":0,"ix":1},"e":{"a":1,"k":[{"i":{"x":[0.667],"y":[1]},"o":{"x":[0.333],"y":[0]},"n":["0p667_1_0p333_0"],"t":27,"s":[0],"e":[100]},{"t":37}],"ix":2},"o":{"a":0,"k":0,"ix":3},"m":1,"ix":2,"nm":"Trim Paths 1","mn":"ADBE Vector Filter - Trim","hd":false}],"ip":27,"op":364,"st":27,"bm":0},{"ddd":0,"ind":3,"ty":4,"nm":"scape1","sr":1,"ks":{"o":{"a":0,"k":100,"ix":11},"r":{"a":1,"k":[{"i":{"x":[0.667],"y":[1]},"o":{"x":[0.333],"y":[0]},"n":["0p667_1_0p333_0"],"t":0,"s":[0],"e":[-5]},{"i":{"x":[0.667],"y":[1]},"o":{"x":[0.333],"y":[0]},"n":["0p667_1_0p333_0"],"t":80,"s":[-5],"e":[3]},{"i":{"x":[0.667],"y":[1]},"o":{"x":[0.333],"y":[0]},"n":["0p667_1_0p333_0"],"t":161,"s":[3],"e":[-5]},{"t":240}],"ix":10},"p":{"a":0,"k":[162.863,246.297,0],"ix":2},"a":{"a":0,"k":[2.737,116.139,0],"ix":1},"s":{"a":0,"k":[100,100,100],"ix":6}},"ao":0,"shapes":[{"ty":"gr","it":[{"ind":0,"ty":"sh","ix":1,"ks":{"a":0,"k":{"i":[[0,0],[-43.741,43.4]],"o":[[0,0],[0,0]],"v":[[-27.238,56.639],[27.238,-56.639]],"c":false},"ix":2},"nm":"Path 1","mn":"ADBE Vector Shape - Group","hd":false},{"ty":"st","c":{"a":0,"k":[0.311000001197,0.119999994016,0.215000002992,1],"ix":3},"o":{"a":0,"k":100,"ix":4},"w":{"a":0,"k":1,"ix":5},"lc":2,"lj":1,"ml":10,"nm":"Stroke 1","mn":"ADBE Vector Graphic - Stroke","hd":false},{"ty":"tr","p":{"a":0,"k":[29.737,59.139],"ix":2},"a":{"a":0,"k":[0,0],"ix":1},"s":{"a":0,"k":[100,100],"ix":3},"r":{"a":0,"k":0,"ix":6},"o":{"a":0,"k":100,"ix":7},"sk":{"a":0,"k":0,"ix":4},"sa":{"a":0,"k":0,"ix":5},"nm":"Transform"}],"nm":"Group 1","np":2,"cix":2,"ix":1,"mn":"ADBE Vector Group","hd":false},{"ty":"tm","s":{"a":0,"k":0,"ix":1},"e":{"a":1,"k":[{"i":{"x":[0.667],"y":[1]},"o":{"x":[0.333],"y":[0]},"n":["0p667_1_0p333_0"],"t":0,"s":[0],"e":[100]},{"t":70}],"ix":2},"o":{"a":0,"k":0,"ix":3},"m":1,"ix":2,"nm":"Trim Paths 1","mn":"ADBE Vector Filter - Trim","hd":false}],"ip":0,"op":337,"st":0,"bm":0},{"ddd":0,"ind":4,"ty":4,"nm":"leave","parent":3,"sr":1,"ks":{"o":{"a":0,"k":100,"ix":11},"r":{"a":1,"k":[{"i":{"x":[0.667],"y":[2.703]},"o":{"x":[0.333],"y":[0.113]},"n":["0p667_2p703_0p333_0p113"],"t":0,"s":[-15],"e":[-16.732]},{"i":{"x":[0.667],"y":[1]},"o":{"x":[0.333],"y":[0.237]},"n":["0p667_1_0p333_0p237"],"t":26,"s":[-16.732],"e":[0]},{"t":61}],"ix":10},"p":{"a":1,"k":[{"i":{"x":0.667,"y":1},"o":{"x":0.333,"y":0},"n":"0p667_1_0p333_0","t":0,"s":[2.374,115.619,0],"e":[20.188,57.713,0],"to":[0,0,0],"ti":[-9.06130981445313,19.6212463378906,0]},{"t":61}],"ix":2},"a":{"a":0,"k":[3.543,56.459,0],"ix":1},"s":{"a":1,"k":[{"i":{"x":[0.667,0.667,0.667],"y":[1,1,1]},"o":{"x":[0.333,0.333,0.333],"y":[0,0,0]},"n":["0p667_1_0p333_0","0p667_1_0p333_0","0p667_1_0p333_0"],"t":0,"s":[0,0,100],"e":[100,100,100]},{"t":70}],"ix":6}},"ao":0,"shapes":[{"ty":"gr","it":[{"ind":0,"ty":"sh","ix":1,"ks":{"a":0,"k":{"i":[[-0.14,0.023],[0.659,-4.001],[0.066,-0.327],[0.878,-2.767],[0.093,-0.316],[0.747,-1.754],[0.416,-0.829],[0.157,-0.321],[2.086,-2.793],[0.234,-0.314],[3.37,-2.669],[0.404,-0.287],[0.343,-0.244],[4.603,1.141],[0,0],[0.172,0.052],[0.077,0.175],[-0.57,5.012],[-0.036,0.209],[-0.075,0.379],[0,0],[-1.529,3.19],[-0.192,0.374],[-0.549,0.929],[-1.628,2.025],[-0.249,0.289],[-2.523,2.091],[-0.267,0.213],[-2.611,1.428],[-0.311,0.152],[-4.664,0.833],[0,0],[-0.114,0.022],[0,0]],"o":[[-0.092,4.693],[-0.053,0.326],[-0.501,2.804],[-0.105,0.318],[-0.582,1.704],[-0.349,0.837],[-0.144,0.32],[-1.54,3.035],[-0.246,0.327],[-2.729,3.51],[-0.401,0.325],[-0.341,0.258],[-3.966,2.789],[0,0],[-0.156,-0.028],[-0.09,-0.173],[-2.226,-4.535],[0.01,-0.22],[0.05,-0.377],[0,0],[0.62,-3.47],[0.178,-0.373],[0.482,-0.963],[1.317,-2.221],[0.237,-0.287],[2.094,-2.51],[0.254,-0.224],[2.321,-1.871],[0.296,-0.177],[4.176,-2.2],[0,0],[0.101,-0.02],[0.012,-0.013],[0.141,-0.023]],"v":[[20.793,-28.96],[19.734,-16.072],[19.562,-15.092],[17.495,-6.792],[17.191,-5.841],[15.204,-0.661],[14.05,1.844],[13.593,2.805],[8.113,11.617],[7.386,12.572],[-1.812,21.939],[-3.019,22.865],[-4.032,23.609],[-16.61,27.818],[-16.623,27.82],[-17.122,27.689],[-17.379,27.167],[-20.223,11.811],[-20.153,11.174],[-19.966,10.053],[-19.967,10.04],[-16.635,0.036],[-16.074,-1.085],[-14.519,-3.917],[-10.097,-10.307],[-9.376,-11.184],[-2.42,-18.121],[-1.631,-18.771],[5.78,-23.733],[6.685,-24.212],[20.005,-28.824],[20.018,-28.826],[20.335,-28.887],[20.36,-28.889]],"c":true},"ix":2},"nm":"Path 1","mn":"ADBE Vector Shape - Group","hd":false},{"ty":"fl","c":{"a":0,"k":[0.366000007181,0.584999952129,0.486999990426,1],"ix":4},"o":{"a":0,"k":100,"ix":5},"r":1,"nm":"Fill 1","mn":"ADBE Vector Graphic - Fill","hd":false},{"ty":"tr","p":{"a":0,"k":[21.043,29.209],"ix":2},"a":{"a":0,"k":[0,0],"ix":1},"s":{"a":0,"k":[100,100],"ix":3},"r":{"a":0,"k":0,"ix":6},"o":{"a":0,"k":100,"ix":7},"sk":{"a":0,"k":0,"ix":4},"sa":{"a":0,"k":0,"ix":5},"nm":"Transform"}],"nm":"Group 1","np":2,"cix":2,"ix":1,"mn":"ADBE Vector Group","hd":false}],"ip":0,"op":337,"st":0,"bm":0}]}],"layers":[{"ddd":0,"ind":1,"ty":0,"nm":"flower2","refId":"comp_0","sr":1,"ks":{"o":{"a":0,"k":100,"ix":11},"r":{"a":0,"k":0,"ix":10},"p":{"a":0,"k":[150,150,0],"ix":2},"a":{"a":0,"k":[150,150,0],"ix":1},"s":{"a":0,"k":[100,100,100],"ix":6}},"ao":0,"w":300,"h":300,"ip":10,"op":241,"st":10,"bm":0},{"ddd":0,"ind":2,"ty":0,"nm":"flower1","refId":"comp_2","sr":1,"ks":{"o":{"a":0,"k":100,"ix":11},"r":{"a":0,"k":0,"ix":10},"p":{"a":0,"k":[150,150,0],"ix":2},"a":{"a":0,"k":[150,150,0],"ix":1},"s":{"a":0,"k":[100,100,100],"ix":6}},"ao":0,"w":300,"h":300,"ip":0,"op":241,"st":0,"bm":0},{"ddd":0,"ind":3,"ty":0,"nm":"live1","refId":"comp_4","sr":1,"ks":{"o":{"a":0,"k":100,"ix":11},"r":{"a":0,"k":-53,"ix":10},"p":{"a":0,"k":[147.5,245.5,0],"ix":2},"a":{"a":0,"k":[163,246,0],"ix":1},"s":{"a":0,"k":[-75,75,100],"ix":6}},"ao":0,"w":300,"h":300,"ip":8,"op":241,"st":8,"bm":0},{"ddd":0,"ind":4,"ty":0,"nm":"live1","refId":"comp_4","sr":1,"ks":{"o":{"a":0,"k":100,"ix":11},"r":{"a":0,"k":0,"ix":10},"p":{"a":0,"k":[150,150,0],"ix":2},"a":{"a":0,"k":[150,150,0],"ix":1},"s":{"a":0,"k":[100,100,100],"ix":6}},"ao":0,"w":300,"h":300,"ip":3,"op":241,"st":3,"bm":0}],"markers":[]}